pow_cli/__init__.py
pow_cli/main.py
pow_cli/data/pow.default.toml
pow_cli/init/TODO.md
pow_cli/lib/__init__.py
pow_cli/lib/path.py
pow_cli/sim/add/__init__.py
pow_cli/sim/add/local_assets.py
pow_cli/sim/check/__init__.py
pow_cli/sim/check/check.py
pow_cli/sim/info/__init__.py
pow_cli/sim/info/info.py
pow_cli/sim/init/__init__.py
pow_cli/sim/init/init_sim.py
pow_cli/sim/run/__init__.py
pow_cli/sim/run/run.py
pow_cli-0.1.0a2.dist-info/METADATA
pow_cli-0.1.0a2.dist-info/WHEEL
pow_cli-0.1.0a2.dist-info/entry_points.txt
pow_cli-0.1.0a2.dist-info/licenses/LICENSE
pow_cli-0.1.0a2.dist-info/licenses/NOTICE
pow_cli-0.1.0a2.dist-info/RECORD
