Metadata-Version: 2.4
Name: pow-cli
Version: 0.1.0a2
Summary: Command line interface for Isaac Powerpack
Author: Titiwat Munintravong, Isaac Powerpack Contributors
License-Expression: Apache-2.0
License-File: LICENSE
License-File: NOTICE
Requires-Python: >=3.10
Requires-Dist: click>=8.1.7
Requires-Dist: toml>=0.10.2
